socks5line/__init__.py
socks5line/__main__.py
socks5line/socks5line.py
socks5line/protocol/__init__.py
socks5line/protocol/socks5.py
socks5line-0.0.4.dist-info/DESCRIPTION.rst
socks5line-0.0.4.dist-info/METADATA
socks5line-0.0.4.dist-info/RECORD
socks5line-0.0.4.dist-info/WHEEL
socks5line-0.0.4.dist-info/metadata.json
socks5line-0.0.4.dist-info/top_level.txt
socks5line-0.0.4.dist-info/zip-safe
